dataframe_column_identifier/LICENSE.md
dataframe_column_identifier/README.md
dataframe_column_identifier/__init__.py
dataframe_column_identifier-0.0.5.dist-info/LICENSE.md
dataframe_column_identifier-0.0.5.dist-info/METADATA
dataframe_column_identifier-0.0.5.dist-info/WHEEL
dataframe_column_identifier-0.0.5.dist-info/top_level.txt
dataframe_column_identifier-0.0.5.dist-info/RECORD
