Metadata-Version: 2.1
Name: dataframe-column-identifier
Version: 0.0.5
Summary: A light and useful package to find columns in a Dataframe by its values.
Home-page: https://github.com/ds-oliveira/dataframe_column_identifier
Author: Danilo Silva de Oliveira
Author-email: danilooliveira28@hotmail.com
License: UNKNOWN
Platform: UNKNOWN
Classifier: Programming Language :: Python :: 3
Classifier: License :: OSI Approved :: MIT License
Classifier: Operating System :: OS Independent
Classifier: Topic :: Scientific/Engineering :: Information Analysis
Requires-Python: >=3.6
Requires-Dist: pandas
Requires-Dist: numpy
